{"session_id": "gen_2", "symbol": "BTCUSDT", "current_generation": 2, "best_reward": 0.0, "karl_state": {"q_values": {}, "q_star_history": "deque([], maxlen=20)", "regime_history": "deque([], maxlen=20)", "historical_qstar": "deque([], maxlen=1000)", "best_chromosomes": [], "oap_weights": {}, "current_q_star": 0.5, "current_regime": "NORMAL", "last_update_gen": 0}, "history": [{"generation": 1, "mean_reward": 0.0, "max_reward": 0.0, "min_reward": 0.0, "std_reward": 0.0, "pool_size": 10, "improvement": 0.0, "top_strategy_id": "8c8e3444-b25", "elapsed_seconds": 0.0, "karl_updated": false}, {"generation": 2, "mean_reward": 0.0, "max_reward": 0.0, "min_reward": 0.0, "std_reward": 0.0, "pool_size": 10, "improvement": 0.0, "top_strategy_id": "01fd530a-fd0", "elapsed_seconds": 0.04, "karl_updated": false}, {"generation": 3, "mean_reward": 0.0, "max_reward": 0.0, "min_reward": 0.0, "std_reward": 0.0, "pool_size": 10, "improvement": 0.0, "top_strategy_id": "990ea112-6b8", "elapsed_seconds": 0.22, "karl_updated": false}], "saved_at": "2026-07-18T08:29:07.190651+00:00"}