{"nodes": [{"id": "home_workspace_astrofin_sentinel_v5_core_rate_limit_py", "label": "rate_limit.py", "file_type": "code", "source_file": "astrofin-sentinel-v5/core/rate_limit.py", "source_location": "L1"}, {"id": "core_rate_limit_is_redis_backed", "label": "is_redis_backed()", "file_type": "code", "source_file": "astrofin-sentinel-v5/core/rate_limit.py", "source_location": "L23"}, {"id": "core_rate_limit_rationale_1", "label": "Rate limiting configuration with optional Redis backend.", "file_type": "rationale", "source_file": "astrofin-sentinel-v5/core/rate_limit.py", "source_location": "L1"}, {"id": "core_rate_limit_rationale_24", "label": "Return True if rate limiter is using Redis.", "file_type": "rationale", "source_file": "astrofin-sentinel-v5/core/rate_limit.py", "source_location": "L24"}], "edges": [{"source": "home_workspace_astrofin_sentinel_v5_core_rate_limit_py", "target": "os", "relation": "imports", "context": "import", "confidence": "EXTRACTED", "source_file": "astrofin-sentinel-v5/core/rate_limit.py", "source_location": "L3", "weight": 1.0}, {"source": "home_workspace_astrofin_sentinel_v5_core_rate_limit_py", "target": "flask_limiter", "relation": "imports_from", "context": "import", "confidence": "EXTRACTED", "source_file": "astrofin-sentinel-v5/core/rate_limit.py", "source_location": "L4", "weight": 1.0}, {"source": "home_workspace_astrofin_sentinel_v5_core_rate_limit_py", "target": "flask_limiter_util", "relation": "imports_from", "context": "import", "confidence": "EXTRACTED", "source_file": "astrofin-sentinel-v5/core/rate_limit.py", "source_location": "L5", "weight": 1.0}, {"source": "home_workspace_astrofin_sentinel_v5_core_rate_limit_py", "target": "core_rate_limit_is_redis_backed", "relation": "contains", "confidence": "EXTRACTED", "source_file": "astrofin-sentinel-v5/core/rate_limit.py", "source_location": "L23", "weight": 1.0}, {"source": "core_rate_limit_rationale_1", "target": "home_workspace_astrofin_sentinel_v5_core_rate_limit_py", "relation": "rationale_for", "confidence": "EXTRACTED", "source_file": "astrofin-sentinel-v5/core/rate_limit.py", "source_location": "L1", "weight": 1.0}, {"source": "core_rate_limit_rationale_24", "target": "core_rate_limit_is_redis_backed", "relation": "rationale_for", "confidence": "EXTRACTED", "source_file": "astrofin-sentinel-v5/core/rate_limit.py", "source_location": "L24", "weight": 1.0}], "raw_calls": []}