{"nodes": [{"id": "home_workspace_home_cluster_iac_scripts_acos_deploy_deploy_sh", "label": "deploy.sh", "file_type": "code", "source_file": "home-cluster-iac/scripts/acos-deploy/deploy.sh", "source_location": "L1", "metadata": {"language": "bash", "kind": "file"}}, {"id": "home_workspace_home_cluster_iac_scripts_acos_deploy_deploy_sh__entry", "label": "deploy.sh script", "file_type": "code", "source_file": "home-cluster-iac/scripts/acos-deploy/deploy.sh", "source_location": "L1", "metadata": {"language": "bash", "kind": "bash_entrypoint"}}, {"id": "acos_deploy_deploy_log", "label": "log()", "file_type": "code", "source_file": "home-cluster-iac/scripts/acos-deploy/deploy.sh", "source_location": "L34", "metadata": {"language": "bash", "kind": "bash_function"}}, {"id": "acos_deploy_deploy_warn", "label": "warn()", "file_type": "code", "source_file": "home-cluster-iac/scripts/acos-deploy/deploy.sh", "source_location": "L35", "metadata": {"language": "bash", "kind": "bash_function"}}, {"id": "acos_deploy_deploy_err", "label": "err()", "file_type": "code", "source_file": "home-cluster-iac/scripts/acos-deploy/deploy.sh", "source_location": "L36", "metadata": {"language": "bash", "kind": "bash_function"}}, {"id": "acos_deploy_deploy_cmd", "label": "cmd()", "file_type": "code", "source_file": "home-cluster-iac/scripts/acos-deploy/deploy.sh", "source_location": "L37", "metadata": {"language": "bash", "kind": "bash_function"}}, {"id": "acos_deploy_deploy_cmd_sudo", "label": "cmd_sudo()", "file_type": "code", "source_file": "home-cluster-iac/scripts/acos-deploy/deploy.sh", "source_location": "L38", "metadata": {"language": "bash", "kind": "bash_function"}}, {"id": "acos_deploy_deploy_is_skipped", "label": "is_skipped()", "file_type": "code", "source_file": "home-cluster-iac/scripts/acos-deploy/deploy.sh", "source_location": "L40", "metadata": {"language": "bash", "kind": "bash_function"}}, {"id": "acos_deploy_deploy_check_reqs", "label": "check_reqs()", "file_type": "code", "source_file": "home-cluster-iac/scripts/acos-deploy/deploy.sh", "source_location": "L46", "metadata": {"language": "bash", "kind": "bash_function"}}, {"id": "acos_deploy_deploy_log_step", "label": "log_step()", "file_type": "code", "source_file": "home-cluster-iac/scripts/acos-deploy/deploy.sh", "source_location": "L54", "metadata": {"language": "bash", "kind": "bash_function"}}, {"id": "acos_deploy_deploy_wait_ssh", "label": "wait_ssh()", "file_type": "code", "source_file": "home-cluster-iac/scripts/acos-deploy/deploy.sh", "source_location": "L58", "metadata": {"language": "bash", "kind": "bash_function"}}, {"id": "acos_deploy_deploy_verify", "label": "verify()", "file_type": "code", "source_file": "home-cluster-iac/scripts/acos-deploy/deploy.sh", "source_location": "L69", "metadata": {"language": "bash", "kind": "bash_function"}}, {"id": "acos_deploy_deploy_deploy_component", "label": "deploy_component()", "file_type": "code", "source_file": "home-cluster-iac/scripts/acos-deploy/deploy.sh", "source_location": "L86", "metadata": {"language": "bash", "kind": "bash_function"}}, {"id": "acos_deploy_deploy_day1", "label": "day1()", "file_type": "code", "source_file": "home-cluster-iac/scripts/acos-deploy/deploy.sh", "source_location": "L94", "metadata": {"language": "bash", "kind": "bash_function"}}, {"id": "acos_deploy_deploy_day2", "label": "day2()", "file_type": "code", "source_file": "home-cluster-iac/scripts/acos-deploy/deploy.sh", "source_location": "L97", "metadata": {"language": "bash", "kind": "bash_function"}}, {"id": "acos_deploy_deploy_day3", "label": "day3()", "file_type": "code", "source_file": "home-cluster-iac/scripts/acos-deploy/deploy.sh", "source_location": "L100", "metadata": {"language": "bash", "kind": "bash_function"}}, {"id": "acos_deploy_deploy_day4", "label": "day4()", "file_type": "code", "source_file": "home-cluster-iac/scripts/acos-deploy/deploy.sh", "source_location": "L103", "metadata": {"language": "bash", "kind": "bash_function"}}, {"id": "acos_deploy_deploy_day5", "label": "day5()", "file_type": "code", "source_file": "home-cluster-iac/scripts/acos-deploy/deploy.sh", "source_location": "L106", "metadata": {"language": "bash", "kind": "bash_function"}}, {"id": "acos_deploy_deploy_day6", "label": "day6()", "file_type": "code", "source_file": "home-cluster-iac/scripts/acos-deploy/deploy.sh", "source_location": "L109", "metadata": {"language": "bash", "kind": "bash_function"}}, {"id": "acos_deploy_deploy_day7", "label": "day7()", "file_type": "code", "source_file": "home-cluster-iac/scripts/acos-deploy/deploy.sh", "source_location": "L112", "metadata": {"language": "bash", "kind": "bash_function"}}, {"id": "acos_deploy_deploy_ml_api", "label": "ml_api()", "file_type": "code", "source_file": "home-cluster-iac/scripts/acos-deploy/deploy.sh", "source_location": "L120", "metadata": {"language": "bash", "kind": "bash_function"}}, {"id": "acos_deploy_deploy_monitor", "label": "monitor()", "file_type": "code", "source_file": "home-cluster-iac/scripts/acos-deploy/deploy.sh", "source_location": "L136", "metadata": {"language": "bash", "kind": "bash_function"}}, {"id": "acos_deploy_deploy_loadtest", "label": "loadtest()", "file_type": "code", "source_file": "home-cluster-iac/scripts/acos-deploy/deploy.sh", "source_location": "L143", "metadata": {"language": "bash", "kind": "bash_function"}}, {"id": "acos_deploy_deploy_self_healing", "label": "self_healing()", "file_type": "code", "source_file": "home-cluster-iac/scripts/acos-deploy/deploy.sh", "source_location": "L153", "metadata": {"language": "bash", "kind": "bash_function"}}, {"id": "acos_deploy_deploy_integration_test", "label": "integration_test()", "file_type": "code", "source_file": "home-cluster-iac/scripts/acos-deploy/deploy.sh", "source_location": "L159", "metadata": {"language": "bash", "kind": "bash_function"}}, {"id": "acos_deploy_deploy_troubleshoot", "label": "troubleshoot()", "file_type": "code", "source_file": "home-cluster-iac/scripts/acos-deploy/deploy.sh", "source_location": "L174", "metadata": {"language": "bash", "kind": "bash_function"}}, {"id": "acos_deploy_deploy_usage", "label": "usage()", "file_type": "code", "source_file": "home-cluster-iac/scripts/acos-deploy/deploy.sh", "source_location": "L189", "metadata": {"language": "bash", "kind": "bash_function"}}, {"id": "acos_deploy_deploy_main", "label": "main()", "file_type": "code", "source_file": "home-cluster-iac/scripts/acos-deploy/deploy.sh", "source_location": "L205", "metadata": {"language": "bash", "kind": "bash_function"}}], "edges": [{"source": "home_workspace_home_cluster_iac_scripts_acos_deploy_deploy_sh", "target": "home_workspace_home_cluster_iac_scripts_acos_deploy_deploy_sh__entry", "relation": "contains", "confidence": "EXTRACTED", "source_file": "home-cluster-iac/scripts/acos-deploy/deploy.sh", "source_location": "L1", "weight": 1.0}, {"source": "home_workspace_home_cluster_iac_scripts_acos_deploy_deploy_sh", "target": "acos_deploy_deploy_log", "relation": "defines", "confidence": "EXTRACTED", "source_file": "home-cluster-iac/scripts/acos-deploy/deploy.sh", "source_location": "L34", "weight": 1.0}, {"source": "home_workspace_home_cluster_iac_scripts_acos_deploy_deploy_sh", "target": "acos_deploy_deploy_warn", "relation": "defines", "confidence": "EXTRACTED", "source_file": "home-cluster-iac/scripts/acos-deploy/deploy.sh", "source_location": "L35", "weight": 1.0}, {"source": "home_workspace_home_cluster_iac_scripts_acos_deploy_deploy_sh", "target": "acos_deploy_deploy_err", "relation": "defines", "confidence": "EXTRACTED", "source_file": "home-cluster-iac/scripts/acos-deploy/deploy.sh", "source_location": "L36", "weight": 1.0}, {"source": "home_workspace_home_cluster_iac_scripts_acos_deploy_deploy_sh", "target": "acos_deploy_deploy_cmd", "relation": "defines", "confidence": "EXTRACTED", "source_file": "home-cluster-iac/scripts/acos-deploy/deploy.sh", "source_location": "L37", "weight": 1.0}, {"source": "home_workspace_home_cluster_iac_scripts_acos_deploy_deploy_sh", "target": "acos_deploy_deploy_cmd_sudo", "relation": "defines", "confidence": "EXTRACTED", "source_file": "home-cluster-iac/scripts/acos-deploy/deploy.sh", "source_location": "L38", "weight": 1.0}, {"source": "home_workspace_home_cluster_iac_scripts_acos_deploy_deploy_sh", "target": "acos_deploy_deploy_is_skipped", "relation": "defines", "confidence": "EXTRACTED", "source_file": "home-cluster-iac/scripts/acos-deploy/deploy.sh", "source_location": "L40", "weight": 1.0}, {"source": "home_workspace_home_cluster_iac_scripts_acos_deploy_deploy_sh", "target": "acos_deploy_deploy_check_reqs", "relation": "defines", "confidence": "EXTRACTED", "source_file": "home-cluster-iac/scripts/acos-deploy/deploy.sh", "source_location": "L46", "weight": 1.0}, {"source": "home_workspace_home_cluster_iac_scripts_acos_deploy_deploy_sh", "target": "acos_deploy_deploy_log_step", "relation": "defines", "confidence": "EXTRACTED", "source_file": "home-cluster-iac/scripts/acos-deploy/deploy.sh", "source_location": "L54", "weight": 1.0}, {"source": "home_workspace_home_cluster_iac_scripts_acos_deploy_deploy_sh", "target": "acos_deploy_deploy_wait_ssh", "relation": "defines", "confidence": "EXTRACTED", "source_file": "home-cluster-iac/scripts/acos-deploy/deploy.sh", "source_location": "L58", "weight": 1.0}, {"source": "home_workspace_home_cluster_iac_scripts_acos_deploy_deploy_sh", "target": "acos_deploy_deploy_verify", "relation": "defines", "confidence": "EXTRACTED", "source_file": "home-cluster-iac/scripts/acos-deploy/deploy.sh", "source_location": "L69", "weight": 1.0}, {"source": "home_workspace_home_cluster_iac_scripts_acos_deploy_deploy_sh", "target": "acos_deploy_deploy_deploy_component", "relation": "defines", "confidence": "EXTRACTED", "source_file": "home-cluster-iac/scripts/acos-deploy/deploy.sh", "source_location": "L86", "weight": 1.0}, {"source": "home_workspace_home_cluster_iac_scripts_acos_deploy_deploy_sh", "target": "acos_deploy_deploy_day1", "relation": "defines", "confidence": "EXTRACTED", "source_file": "home-cluster-iac/scripts/acos-deploy/deploy.sh", "source_location": "L94", "weight": 1.0}, {"source": "home_workspace_home_cluster_iac_scripts_acos_deploy_deploy_sh", "target": "acos_deploy_deploy_day2", "relation": "defines", "confidence": "EXTRACTED", "source_file": "home-cluster-iac/scripts/acos-deploy/deploy.sh", "source_location": "L97", "weight": 1.0}, {"source": "home_workspace_home_cluster_iac_scripts_acos_deploy_deploy_sh", "target": "acos_deploy_deploy_day3", "relation": "defines", "confidence": "EXTRACTED", "source_file": "home-cluster-iac/scripts/acos-deploy/deploy.sh", "source_location": "L100", "weight": 1.0}, {"source": "home_workspace_home_cluster_iac_scripts_acos_deploy_deploy_sh", "target": "acos_deploy_deploy_day4", "relation": "defines", "confidence": "EXTRACTED", "source_file": "home-cluster-iac/scripts/acos-deploy/deploy.sh", "source_location": "L103", "weight": 1.0}, {"source": "home_workspace_home_cluster_iac_scripts_acos_deploy_deploy_sh", "target": "acos_deploy_deploy_day5", "relation": "defines", "confidence": "EXTRACTED", "source_file": "home-cluster-iac/scripts/acos-deploy/deploy.sh", "source_location": "L106", "weight": 1.0}, {"source": "home_workspace_home_cluster_iac_scripts_acos_deploy_deploy_sh", "target": "acos_deploy_deploy_day6", "relation": "defines", "confidence": "EXTRACTED", "source_file": "home-cluster-iac/scripts/acos-deploy/deploy.sh", "source_location": "L109", "weight": 1.0}, {"source": "home_workspace_home_cluster_iac_scripts_acos_deploy_deploy_sh", "target": "acos_deploy_deploy_day7", "relation": "defines", "confidence": "EXTRACTED", "source_file": "home-cluster-iac/scripts/acos-deploy/deploy.sh", "source_location": "L112", "weight": 1.0}, {"source": "home_workspace_home_cluster_iac_scripts_acos_deploy_deploy_sh", "target": "acos_deploy_deploy_ml_api", "relation": "defines", "confidence": "EXTRACTED", "source_file": "home-cluster-iac/scripts/acos-deploy/deploy.sh", "source_location": "L120", "weight": 1.0}, {"source": "home_workspace_home_cluster_iac_scripts_acos_deploy_deploy_sh", "target": "acos_deploy_deploy_monitor", "relation": "defines", "confidence": "EXTRACTED", "source_file": "home-cluster-iac/scripts/acos-deploy/deploy.sh", "source_location": "L136", "weight": 1.0}, {"source": "home_workspace_home_cluster_iac_scripts_acos_deploy_deploy_sh", "target": "acos_deploy_deploy_loadtest", "relation": "defines", "confidence": "EXTRACTED", "source_file": "home-cluster-iac/scripts/acos-deploy/deploy.sh", "source_location": "L143", "weight": 1.0}, {"source": "home_workspace_home_cluster_iac_scripts_acos_deploy_deploy_sh", "target": "acos_deploy_deploy_self_healing", "relation": "defines", "confidence": "EXTRACTED", "source_file": "home-cluster-iac/scripts/acos-deploy/deploy.sh", "source_location": "L153", "weight": 1.0}, {"source": "home_workspace_home_cluster_iac_scripts_acos_deploy_deploy_sh", "target": "acos_deploy_deploy_integration_test", "relation": "defines", "confidence": "EXTRACTED", "source_file": "home-cluster-iac/scripts/acos-deploy/deploy.sh", "source_location": "L159", "weight": 1.0}, {"source": "home_workspace_home_cluster_iac_scripts_acos_deploy_deploy_sh", "target": "acos_deploy_deploy_troubleshoot", "relation": "defines", "confidence": "EXTRACTED", "source_file": "home-cluster-iac/scripts/acos-deploy/deploy.sh", "source_location": "L174", "weight": 1.0}, {"source": "home_workspace_home_cluster_iac_scripts_acos_deploy_deploy_sh", "target": "acos_deploy_deploy_usage", "relation": "defines", "confidence": "EXTRACTED", "source_file": "home-cluster-iac/scripts/acos-deploy/deploy.sh", "source_location": "L189", "weight": 1.0}, {"source": "home_workspace_home_cluster_iac_scripts_acos_deploy_deploy_sh", "target": "acos_deploy_deploy_main", "relation": "defines", "confidence": "EXTRACTED", "source_file": "home-cluster-iac/scripts/acos-deploy/deploy.sh", "source_location": "L205", "weight": 1.0}, {"source": "home_workspace_home_cluster_iac_scripts_acos_deploy_deploy_sh__entry", "target": "acos_deploy_deploy_log", "relation": "calls", "confidence": "EXTRACTED", "source_file": "home-cluster-iac/scripts/acos-deploy/deploy.sh", "source_location": "L26", "weight": 1.0, "context": "call"}, {"source": "home_workspace_home_cluster_iac_scripts_acos_deploy_deploy_sh__entry", "target": "acos_deploy_deploy_main", "relation": "calls", "confidence": "EXTRACTED", "source_file": "home-cluster-iac/scripts/acos-deploy/deploy.sh", "source_location": "L231", "weight": 1.0, "context": "call"}, {"source": "acos_deploy_deploy_cmd", "target": "acos_deploy_deploy_log", "relation": "calls", "confidence": "EXTRACTED", "source_file": "home-cluster-iac/scripts/acos-deploy/deploy.sh", "source_location": "L37", "weight": 1.0, "context": "call"}, {"source": "acos_deploy_deploy_check_reqs", "target": "acos_deploy_deploy_err", "relation": "calls", "confidence": "EXTRACTED", "source_file": "home-cluster-iac/scripts/acos-deploy/deploy.sh", "source_location": "L48", "weight": 1.0, "context": "call"}, {"source": "acos_deploy_deploy_log_step", "target": "acos_deploy_deploy_log", "relation": "calls", "confidence": "EXTRACTED", "source_file": "home-cluster-iac/scripts/acos-deploy/deploy.sh", "source_location": "L55", "weight": 1.0, "context": "call"}, {"source": "acos_deploy_deploy_wait_ssh", "target": "acos_deploy_deploy_log", "relation": "calls", "confidence": "EXTRACTED", "source_file": "home-cluster-iac/scripts/acos-deploy/deploy.sh", "source_location": "L60", "weight": 1.0, "context": "call"}, {"source": "acos_deploy_deploy_wait_ssh", "target": "acos_deploy_deploy_warn", "relation": "calls", "confidence": "EXTRACTED", "source_file": "home-cluster-iac/scripts/acos-deploy/deploy.sh", "source_location": "L65", "weight": 1.0, "context": "call"}, {"source": "acos_deploy_deploy_verify", "target": "acos_deploy_deploy_log_step", "relation": "calls", "confidence": "EXTRACTED", "source_file": "home-cluster-iac/scripts/acos-deploy/deploy.sh", "source_location": "L70", "weight": 1.0, "context": "call"}, {"source": "acos_deploy_deploy_verify", "target": "acos_deploy_deploy_cmd", "relation": "calls", "confidence": "EXTRACTED", "source_file": "home-cluster-iac/scripts/acos-deploy/deploy.sh", "source_location": "L72", "weight": 1.0, "context": "call"}, {"source": "acos_deploy_deploy_verify", "target": "acos_deploy_deploy_warn", "relation": "calls", "confidence": "EXTRACTED", "source_file": "home-cluster-iac/scripts/acos-deploy/deploy.sh", "source_location": "L72", "weight": 1.0, "context": "call"}, {"source": "acos_deploy_deploy_verify", "target": "acos_deploy_deploy_cmd_sudo", "relation": "calls", "confidence": "EXTRACTED", "source_file": "home-cluster-iac/scripts/acos-deploy/deploy.sh", "source_location": "L80", "weight": 1.0, "context": "call"}, {"source": "acos_deploy_deploy_deploy_component", "target": "acos_deploy_deploy_log_step", "relation": "calls", "confidence": "EXTRACTED", "source_file": "home-cluster-iac/scripts/acos-deploy/deploy.sh", "source_location": "L88", "weight": 1.0, "context": "call"}, {"source": "acos_deploy_deploy_day1", "target": "acos_deploy_deploy_deploy_component", "relation": "calls", "confidence": "EXTRACTED", "source_file": "home-cluster-iac/scripts/acos-deploy/deploy.sh", "source_location": "L95", "weight": 1.0, "context": "call"}, {"source": "acos_deploy_deploy_day2", "target": "acos_deploy_deploy_deploy_component", "relation": "calls", "confidence": "EXTRACTED", "source_file": "home-cluster-iac/scripts/acos-deploy/deploy.sh", "source_location": "L98", "weight": 1.0, "context": "call"}, {"source": "acos_deploy_deploy_day3", "target": "acos_deploy_deploy_deploy_component", "relation": "calls", "confidence": "EXTRACTED", "source_file": "home-cluster-iac/scripts/acos-deploy/deploy.sh", "source_location": "L101", "weight": 1.0, "context": "call"}, {"source": "acos_deploy_deploy_day4", "target": "acos_deploy_deploy_deploy_component", "relation": "calls", "confidence": "EXTRACTED", "source_file": "home-cluster-iac/scripts/acos-deploy/deploy.sh", "source_location": "L104", "weight": 1.0, "context": "call"}, {"source": "acos_deploy_deploy_day5", "target": "acos_deploy_deploy_deploy_component", "relation": "calls", "confidence": "EXTRACTED", "source_file": "home-cluster-iac/scripts/acos-deploy/deploy.sh", "source_location": "L107", "weight": 1.0, "context": "call"}, {"source": "acos_deploy_deploy_day6", "target": "acos_deploy_deploy_deploy_component", "relation": "calls", "confidence": "EXTRACTED", "source_file": "home-cluster-iac/scripts/acos-deploy/deploy.sh", "source_location": "L110", "weight": 1.0, "context": "call"}, {"source": "acos_deploy_deploy_day7", "target": "acos_deploy_deploy_log_step", "relation": "calls", "confidence": "EXTRACTED", "source_file": "home-cluster-iac/scripts/acos-deploy/deploy.sh", "source_location": "L113", "weight": 1.0, "context": "call"}, {"source": "acos_deploy_deploy_day7", "target": "acos_deploy_deploy_deploy_component", "relation": "calls", "confidence": "EXTRACTED", "source_file": "home-cluster-iac/scripts/acos-deploy/deploy.sh", "source_location": "L114", "weight": 1.0, "context": "call"}, {"source": "acos_deploy_deploy_ml_api", "target": "acos_deploy_deploy_log_step", "relation": "calls", "confidence": "EXTRACTED", "source_file": "home-cluster-iac/scripts/acos-deploy/deploy.sh", "source_location": "L121", "weight": 1.0, "context": "call"}, {"source": "acos_deploy_deploy_ml_api", "target": "acos_deploy_deploy_cmd", "relation": "calls", "confidence": "EXTRACTED", "source_file": "home-cluster-iac/scripts/acos-deploy/deploy.sh", "source_location": "L122", "weight": 1.0, "context": "call"}, {"source": "acos_deploy_deploy_ml_api", "target": "acos_deploy_deploy_log", "relation": "calls", "confidence": "EXTRACTED", "source_file": "home-cluster-iac/scripts/acos-deploy/deploy.sh", "source_location": "L124", "weight": 1.0, "context": "call"}, {"source": "acos_deploy_deploy_ml_api", "target": "acos_deploy_deploy_cmd_sudo", "relation": "calls", "confidence": "EXTRACTED", "source_file": "home-cluster-iac/scripts/acos-deploy/deploy.sh", "source_location": "L125", "weight": 1.0, "context": "call"}, {"source": "acos_deploy_deploy_ml_api", "target": "acos_deploy_deploy_warn", "relation": "calls", "confidence": "EXTRACTED", "source_file": "home-cluster-iac/scripts/acos-deploy/deploy.sh", "source_location": "L132", "weight": 1.0, "context": "call"}, {"source": "acos_deploy_deploy_monitor", "target": "acos_deploy_deploy_log_step", "relation": "calls", "confidence": "EXTRACTED", "source_file": "home-cluster-iac/scripts/acos-deploy/deploy.sh", "source_location": "L137", "weight": 1.0, "context": "call"}, {"source": "acos_deploy_deploy_monitor", "target": "acos_deploy_deploy_deploy_component", "relation": "calls", "confidence": "EXTRACTED", "source_file": "home-cluster-iac/scripts/acos-deploy/deploy.sh", "source_location": "L138", "weight": 1.0, "context": "call"}, {"source": "acos_deploy_deploy_monitor", "target": "acos_deploy_deploy_log", "relation": "calls", "confidence": "EXTRACTED", "source_file": "home-cluster-iac/scripts/acos-deploy/deploy.sh", "source_location": "L139", "weight": 1.0, "context": "call"}, {"source": "acos_deploy_deploy_loadtest", "target": "acos_deploy_deploy_log_step", "relation": "calls", "confidence": "EXTRACTED", "source_file": "home-cluster-iac/scripts/acos-deploy/deploy.sh", "source_location": "L144", "weight": 1.0, "context": "call"}, {"source": "acos_deploy_deploy_loadtest", "target": "acos_deploy_deploy_warn", "relation": "calls", "confidence": "EXTRACTED", "source_file": "home-cluster-iac/scripts/acos-deploy/deploy.sh", "source_location": "L146", "weight": 1.0, "context": "call"}, {"source": "acos_deploy_deploy_loadtest", "target": "acos_deploy_deploy_cmd", "relation": "calls", "confidence": "EXTRACTED", "source_file": "home-cluster-iac/scripts/acos-deploy/deploy.sh", "source_location": "L149", "weight": 1.0, "context": "call"}, {"source": "acos_deploy_deploy_self_healing", "target": "acos_deploy_deploy_log_step", "relation": "calls", "confidence": "EXTRACTED", "source_file": "home-cluster-iac/scripts/acos-deploy/deploy.sh", "source_location": "L154", "weight": 1.0, "context": "call"}, {"source": "acos_deploy_deploy_self_healing", "target": "acos_deploy_deploy_deploy_component", "relation": "calls", "confidence": "EXTRACTED", "source_file": "home-cluster-iac/scripts/acos-deploy/deploy.sh", "source_location": "L155", "weight": 1.0, "context": "call"}, {"source": "acos_deploy_deploy_integration_test", "target": "acos_deploy_deploy_log_step", "relation": "calls", "confidence": "EXTRACTED", "source_file": "home-cluster-iac/scripts/acos-deploy/deploy.sh", "source_location": "L160", "weight": 1.0, "context": "call"}, {"source": "acos_deploy_deploy_integration_test", "target": "acos_deploy_deploy_log", "relation": "calls", "confidence": "EXTRACTED", "source_file": "home-cluster-iac/scripts/acos-deploy/deploy.sh", "source_location": "L162", "weight": 1.0, "context": "call"}, {"source": "acos_deploy_deploy_integration_test", "target": "acos_deploy_deploy_cmd", "relation": "calls", "confidence": "EXTRACTED", "source_file": "home-cluster-iac/scripts/acos-deploy/deploy.sh", "source_location": "L164", "weight": 1.0, "context": "call"}, {"source": "acos_deploy_deploy_integration_test", "target": "acos_deploy_deploy_warn", "relation": "calls", "confidence": "EXTRACTED", "source_file": "home-cluster-iac/scripts/acos-deploy/deploy.sh", "source_location": "L169", "weight": 1.0, "context": "call"}, {"source": "acos_deploy_deploy_troubleshoot", "target": "acos_deploy_deploy_log_step", "relation": "calls", "confidence": "EXTRACTED", "source_file": "home-cluster-iac/scripts/acos-deploy/deploy.sh", "source_location": "L175", "weight": 1.0, "context": "call"}, {"source": "acos_deploy_deploy_troubleshoot", "target": "acos_deploy_deploy_cmd_sudo", "relation": "calls", "confidence": "EXTRACTED", "source_file": "home-cluster-iac/scripts/acos-deploy/deploy.sh", "source_location": "L177", "weight": 1.0, "context": "call"}, {"source": "acos_deploy_deploy_troubleshoot", "target": "acos_deploy_deploy_cmd", "relation": "calls", "confidence": "EXTRACTED", "source_file": "home-cluster-iac/scripts/acos-deploy/deploy.sh", "source_location": "L179", "weight": 1.0, "context": "call"}, {"source": "acos_deploy_deploy_main", "target": "acos_deploy_deploy_check_reqs", "relation": "calls", "confidence": "EXTRACTED", "source_file": "home-cluster-iac/scripts/acos-deploy/deploy.sh", "source_location": "L206", "weight": 1.0, "context": "call"}, {"source": "acos_deploy_deploy_main", "target": "acos_deploy_deploy_usage", "relation": "calls", "confidence": "EXTRACTED", "source_file": "home-cluster-iac/scripts/acos-deploy/deploy.sh", "source_location": "L208", "weight": 1.0, "context": "call"}, {"source": "acos_deploy_deploy_main", "target": "acos_deploy_deploy_day1", "relation": "calls", "confidence": "EXTRACTED", "source_file": "home-cluster-iac/scripts/acos-deploy/deploy.sh", "source_location": "L211", "weight": 1.0, "context": "call"}, {"source": "acos_deploy_deploy_main", "target": "acos_deploy_deploy_day2", "relation": "calls", "confidence": "EXTRACTED", "source_file": "home-cluster-iac/scripts/acos-deploy/deploy.sh", "source_location": "L212", "weight": 1.0, "context": "call"}, {"source": "acos_deploy_deploy_main", "target": "acos_deploy_deploy_day3", "relation": "calls", "confidence": "EXTRACTED", "source_file": "home-cluster-iac/scripts/acos-deploy/deploy.sh", "source_location": "L213", "weight": 1.0, "context": "call"}, {"source": "acos_deploy_deploy_main", "target": "acos_deploy_deploy_day4", "relation": "calls", "confidence": "EXTRACTED", "source_file": "home-cluster-iac/scripts/acos-deploy/deploy.sh", "source_location": "L214", "weight": 1.0, "context": "call"}, {"source": "acos_deploy_deploy_main", "target": "acos_deploy_deploy_day5", "relation": "calls", "confidence": "EXTRACTED", "source_file": "home-cluster-iac/scripts/acos-deploy/deploy.sh", "source_location": "L215", "weight": 1.0, "context": "call"}, {"source": "acos_deploy_deploy_main", "target": "acos_deploy_deploy_day6", "relation": "calls", "confidence": "EXTRACTED", "source_file": "home-cluster-iac/scripts/acos-deploy/deploy.sh", "source_location": "L216", "weight": 1.0, "context": "call"}, {"source": "acos_deploy_deploy_main", "target": "acos_deploy_deploy_day7", "relation": "calls", "confidence": "EXTRACTED", "source_file": "home-cluster-iac/scripts/acos-deploy/deploy.sh", "source_location": "L217", "weight": 1.0, "context": "call"}, {"source": "acos_deploy_deploy_main", "target": "acos_deploy_deploy_verify", "relation": "calls", "confidence": "EXTRACTED", "source_file": "home-cluster-iac/scripts/acos-deploy/deploy.sh", "source_location": "L218", "weight": 1.0, "context": "call"}, {"source": "acos_deploy_deploy_main", "target": "acos_deploy_deploy_ml_api", "relation": "calls", "confidence": "EXTRACTED", "source_file": "home-cluster-iac/scripts/acos-deploy/deploy.sh", "source_location": "L220", "weight": 1.0, "context": "call"}, {"source": "acos_deploy_deploy_main", "target": "acos_deploy_deploy_monitor", "relation": "calls", "confidence": "EXTRACTED", "source_file": "home-cluster-iac/scripts/acos-deploy/deploy.sh", "source_location": "L221", "weight": 1.0, "context": "call"}, {"source": "acos_deploy_deploy_main", "target": "acos_deploy_deploy_loadtest", "relation": "calls", "confidence": "EXTRACTED", "source_file": "home-cluster-iac/scripts/acos-deploy/deploy.sh", "source_location": "L222", "weight": 1.0, "context": "call"}, {"source": "acos_deploy_deploy_main", "target": "acos_deploy_deploy_self_healing", "relation": "calls", "confidence": "EXTRACTED", "source_file": "home-cluster-iac/scripts/acos-deploy/deploy.sh", "source_location": "L223", "weight": 1.0, "context": "call"}, {"source": "acos_deploy_deploy_main", "target": "acos_deploy_deploy_integration_test", "relation": "calls", "confidence": "EXTRACTED", "source_file": "home-cluster-iac/scripts/acos-deploy/deploy.sh", "source_location": "L224", "weight": 1.0, "context": "call"}, {"source": "acos_deploy_deploy_main", "target": "acos_deploy_deploy_troubleshoot", "relation": "calls", "confidence": "EXTRACTED", "source_file": "home-cluster-iac/scripts/acos-deploy/deploy.sh", "source_location": "L225", "weight": 1.0, "context": "call"}, {"source": "acos_deploy_deploy_main", "target": "acos_deploy_deploy_err", "relation": "calls", "confidence": "EXTRACTED", "source_file": "home-cluster-iac/scripts/acos-deploy/deploy.sh", "source_location": "L227", "weight": 1.0, "context": "call"}]}